Workbook

Sheet Premissas
A1: Premissas do modelo
A2: Edite apenas as células AMARELAS. Todo o resto é calculado a partir delas.
A4: RECEITA
A5: Ticket médio mensal por cliente | B5: 97 | C5: Plano Pro como carro-chefe. Premissa não validada.
A6: Churn mensal | B6: 0.03 | C6: Benchmark de SaaS B2B brasileiro, não do nosso nicho.
A8: CUSTOS VARIÁVEIS POR CLIENTE
A9: Taxa percentual do gateway | B9: 0.039 | C9: Stripe Brasil: 3,9% + R$0,39 por transação bem-sucedida.
A10: Taxa fixa do gateway | B10: 0.39
A11: Alíquota do Simples COM Fator R (Anexo III) | B11: 0.073 | C11: Faixa de R$240 mil/ano. Na 1a faixa (ate R$180 mil/ano) e 6,0%.
A12: Alíquota do Simples SEM Fator R (Anexo V) | B12: 0.155 | C12: 1a faixa do Anexo V. Usada quando a folha fica abaixo de 28% da receita.
A13: Infraestrutura variável por cliente | B13: 1.5 | C13: Sem sessão de WhatsApp conectada, o custo por cliente é mínimo.
A15: CUSTOS FIXOS MENSAIS
A16: VPS (aplicação, banco e workers) | B16: 150 | C16: Hetzner CX42 16GB ≈ R$96. Folga incluída.
A17: Proxies residenciais | B17: 150 | C17: Uso reduzido: Shopee e Awin são API oficial.
A18: Contabilidade | B18: 300
A19: Observabilidade e ferramentas | B19: 200
A20: Domínio e e-mail transacional | B20: 50
A21: Total de custos fixos mensais | B21: =SUM(B16:B20) -> 850
A23: REMUNERAÇÃO DOS SÓCIOS
A24: Pró-labore mensal por sócio | B24: 3000
A25: Número de sócios com pró-labore | B25: 2
A26: Total de pró-labore | B26: =B24*B25 -> 6000 | C26: O Fator R exige folha ≥28% da receita para manter o Anexo III.
A28: AQUISIÇÃO — NOVOS CLIENTES POR MÊS
A29: Cenário conservador | B29: 5
A30: Cenário base | B30: 15
A31: Cenário otimista | B31: 35 | C31: Estimativa. Substituir por dado real após os primeiros 60 dias.
A33: PARÂMETROS DE REFERÊNCIA
A34: Múltiplo LTV:CAC alvo | B34: 3 | C34: Benchmark: >=3:1 e saudavel; 4 a 6:1 e excelente.
A35: Churn alternativo para teste de sensibilidade | B35: 0.06 | C35: Micro-SaaS de ticket baixo para criadores costuma ficar entre 4% e 8%.
A36: Fator R: folha minima exigida sobre a receita | B36: 0.28 | C36: Abaixo disso a empresa cai no Anexo V e a margem encolhe.
A39: LEGENDA
A40: Amarelo com texto azul = entrada editável • Preto = fórmula • Verde = valor de outra aba

Sheet Unit Economics
A1: Unit economics por cliente
A2: Calculado a partir da aba Premissas. Verde indica valor vindo de outra aba.
A4: COMPOSIÇÃO DA MARGEM
A5: Receita mensal por cliente | B5: =Premissas!B5 -> 97
A6: Taxa do gateway | B6: =-(Premissas!B5*Premissas!B9+Premissas!B10) -> -4.173
A7: Simples Nacional | B7: =-(Premissas!B5*Premissas!B11) -> -7.081
A8: Infraestrutura variável | B8: =-Premissas!B13 -> -1.5
A9: Margem de contribuição por cliente | B9: =SUM(B5:B8) -> 84.246
A10: Margem de contribuição (%) | B10: =B9/B5 -> 0.86851546
A12: VALOR DO CLIENTE
A13: Tempo médio de permanência (meses) | B13: =1/Premissas!B6 -> 33.333333 | C13: Inverso do churn mensal.
A14: LTV — valor total do cliente | B14: =B9/Premissas!B6 -> 2808.2
A15: CAC máximo sustentável | B15: =B14/Premissas!B34 -> 936.06667 | C15: Teto de gasto para adquirir um cliente mantendo o multiplo alvo.
A17: TESTE DE SENSIBILIDADE
A18: Margem SEM Fator R (Anexo V) | B18: =Premissas!B5-(Premissas!B5*Premissas!B9+Premissas!B10)-(Premissas!B5*Premissas!B12)-Premissas!B13 -> 76.292 | C18: Cenario em que a folha nao atinge 28% da receita.
A19: LTV com churn alternativo | B19: =B9/Premissas!B35 -> 1404.1
A20: CAC máximo com churn alternativo | B20: =B19/Premissas!B34 -> 468.03333 | C20: Se o churn real for o do segmento de criadores, o teto de CAC cai pela metade.
A21: Receita máxima que o pró-labore atual sustenta no Fator R | B21: =Premissas!B26/Premissas!B36 -> 21428.571 | C21: Acima desta receita, e preciso aumentar a folha ou perder o Anexo III.
A24: LEGENDA
A25: Amarelo com texto azul = entrada editável • Preto = fórmula • Verde = valor de outra aba

Sheet Break-even
A1: Ponto de equilíbrio
A2: Quantos clientes pagantes são necessários em cada nível de compromisso.
A4: BASE DE CÁLCULO
A5: Margem de contribuição por cliente | B5: ='Unit Economics'!B9 -> 84.246
A6: Custo fixo mensal | B6: =Premissas!B21 -> 850
A7: Pró-labore total | B7: =Premissas!B26 -> 6000
A9: CLIENTES NECESSÁRIOS
A10: Para cobrir o custo operacional (COM Fator R) | B10: =ROUNDUP(B6/B5,0) -> 11 | C10: So valido se houver folha >=28% da receita. Sem pro-labore, use a linha da secao Sensibilidade.
A11: Para cobrir custo operacional + pró-labore | B11: =ROUNDUP((B6+B7)/B5,0) -> 82 | C11: A partir daqui o negócio remunera os sócios.
A12: Receita mensal no ponto de equilíbrio operacional | B12: =B10*Premissas!B5 -> 1067
A14: SENSIBILIDADE
A15: Para cobrir o custo operacional SEM pró-labore (Anexo V) | B15: =ROUNDUP(B6/'Unit Economics'!B18,0) -> 12 | C15: Sem folha nao ha Fator R. Este e o numero honesto para o cenario sem pro-labore.
A16: Clientes para custo + pró-labore, com churn alternativo | B16: =ROUNDUP((B6+B7)/B5,0) -> 82 | C16: O break-even nao muda com churn; o que muda e o tempo para chegar la.
A19: LEGENDA
A20: Amarelo com texto azul = entrada editável • Preto = fórmula • Verde = valor de outra aba

Sheet Cenários
A1: Projeção de 12 meses após o lançamento
A2: Três cenários de aquisição. Resultado é operacional, antes de pró-labore.
B3: CONSERVADOR | E3: BASE | H3: OTIMISTA
A4: Mês | B4: Clientes | C4: Receita | D4: Resultado | E4: Clientes | F4: Receita | G4: Resultado | H4: Clientes | I4: Receita | J4: Resultado
A5: 1 | B5: =Premissas!$B$29 -> 5 | C5: =B5*Premissas!$B$5 -> 485 | D5: =B5*'Unit Economics'!$B$9-Premissas!$B$21 -> -428.77 | E5: =Premissas!$B$30 -> 15 | F5: =E5*Premissas!$B$5 -> 1455 | G5: =E5*'Unit Economics'!$B$9-Premissas!$B$21 -> 413.69 | H5: =Premissas!$B$31 -> 35 | I5: =H5*Premissas!$B$5 -> 3395 | J5: =H5*'Unit Economics'!$B$9-Premissas!$B$21 -> 2098.61
A6: 2 | B6: =B5*(1-Premissas!$B$6)+Premissas!$B$29 -> 9.85 | C6: =B6*Premissas!$B$5 -> 955.45 | D6: =B6*'Unit Economics'!$B$9-Premissas!$B$21 -> -20.1769 | E6: =E5*(1-Premissas!$B$6)+Premissas!$B$30 -> 29.55 | F6: =E6*Premissas!$B$5 -> 2866.35 | G6: =E6*'Unit Economics'!$B$9-Premissas!$B$21 -> 1639.4693 | H6: =H5*(1-Premissas!$B$6)+Premissas!$B$31 -> 68.95 | I6: =H6*Premissas!$B$5 -> 6688.15 | J6: =H6*'Unit Economics'!$B$9-Premissas!$B$21 -> 4958.7617
A7: 3 | B7: =B6*(1-Premissas!$B$6)+Premissas!$B$29 -> 14.5545 | C7: =B7*Premissas!$B$5 -> 1411.7865 | D7: =B7*'Unit Economics'!$B$9-Premissas!$B$21 -> 376.15841 | E7: =E6*(1-Premissas!$B$6)+Premissas!$B$30 -> 43.6635 | F7: =E7*Premissas!$B$5 -> 4235.3595 | G7: =E7*'Unit Economics'!$B$9-Premissas!$B$21 -> 2828.4752 | H7: =H6*(1-Premissas!$B$6)+Premissas!$B$31 -> 101.8815 | I7: =H7*Premissas!$B$5 -> 9882.5055 | J7: =H7*'Unit Economics'!$B$9-Premissas!$B$21 -> 7733.1088
A8: 4 | B8: =B7*(1-Premissas!$B$6)+Premissas!$B$29 -> 19.117865 | C8: =B8*Premissas!$B$5 -> 1854.4329 | D8: =B8*'Unit Economics'!$B$9-Premissas!$B$21 -> 760.60365 | E8: =E7*(1-Premissas!$B$6)+Premissas!$B$30 -> 57.353595 | F8: =E8*Premissas!$B$5 -> 5563.2987 | G8: =E8*'Unit Economics'!$B$9-Premissas!$B$21 -> 3981.811 | H8: =H7*(1-Premissas!$B$6)+Premissas!$B$31 -> 133.82505 | I8: =H8*Premissas!$B$5 -> 12981.03 | J8: =H8*'Unit Economics'!$B$9-Premissas!$B$21 -> 10424.226
A9: 5 | B9: =B8*(1-Premissas!$B$6)+Premissas!$B$29 -> 23.544329 | C9: =B9*Premissas!$B$5 -> 2283.7999 | D9: =B9*'Unit Economics'!$B$9-Premissas!$B$21 -> 1133.5155 | E9: =E8*(1-Premissas!$B$6)+Premissas!$B$30 -> 70.632987 | F9: =E9*Premissas!$B$5 -> 6851.3998 | G9: =E9*'Unit Economics'!$B$9-Premissas!$B$21 -> 5100.5466 | H9: =H8*(1-Premissas!$B$6)+Premissas!$B$31 -> 164.8103 | I9: =H9*Premissas!$B$5 -> 15986.599 | J9: =H9*'Unit Economics'!$B$9-Premissas!$B$21 -> 13034.609
A10: 6 | B10: =B9*(1-Premissas!$B$6)+Premissas!$B$29 -> 27.837999 | C10: =B10*Premissas!$B$5 -> 2700.2859 | D10: =B10*'Unit Economics'!$B$9-Premissas!$B$21 -> 1495.2401 | E10: =E9*(1-Premissas!$B$6)+Premissas!$B$30 -> 83.513998 | F10: =E10*Premissas!$B$5 -> 8100.8578 | G10: =E10*'Unit Economics'!$B$9-Premissas!$B$21 -> 6185.7202 | H10: =H9*(1-Premissas!$B$6)+Premissas!$B$31 -> 194.86599 | I10: =H10*Premissas!$B$5 -> 18902.001 | J10: =H10*'Unit Economics'!$B$9-Premissas!$B$21 -> 15566.681
A11: 7 | B11: =B10*(1-Premissas!$B$6)+Premissas!$B$29 -> 32.002859 | C11: =B11*Premissas!$B$5 -> 3104.2773 | D11: =B11*'Unit Economics'!$B$9-Premissas!$B$21 -> 1846.1129 | E11: =E10*(1-Premissas!$B$6)+Premissas!$B$30 -> 96.008578 | F11: =E11*Premissas!$B$5 -> 9312.832 | G11: =E11*'Unit Economics'!$B$9-Premissas!$B$21 -> 7238.3386 | H11: =H10*(1-Premissas!$B$6)+Premissas!$B$31 -> 224.02001 | I11: =H11*Premissas!$B$5 -> 21729.941 | J11: =H11*'Unit Economics'!$B$9-Premissas!$B$21 -> 18022.79
A12: 8 | B12: =B11*(1-Premissas!$B$6)+Premissas!$B$29 -> 36.042773 | C12: =B12*Premissas!$B$5 -> 3496.149 | D12: =B12*'Unit Economics'!$B$9-Premissas!$B$21 -> 2186.4595 | E12: =E11*(1-Premissas!$B$6)+Premissas!$B$30 -> 108.12832 | F12: =E12*Premissas!$B$5 -> 10488.447 | G12: =E12*'Unit Economics'!$B$9-Premissas!$B$21 -> 8259.3785 | H12: =H11*(1-Premissas!$B$6)+Premissas!$B$31 -> 252.29941 | I12: =H12*Premissas!$B$5 -> 24473.043 | J12: =H12*'Unit Economics'!$B$9-Premissas!$B$21 -> 20405.216
A13: 9 | B13: =B12*(1-Premissas!$B$6)+Premissas!$B$29 -> 39.96149 | C13: =B13*Premissas!$B$5 -> 3876.2646 | D13: =B13*'Unit Economics'!$B$9-Premissas!$B$21 -> 2516.5957 | E13: =E12*(1-Premissas!$B$6)+Premissas!$B$30 -> 119.88447 | F13: =E13*Premissas!$B$5 -> 11628.794 | G13: =E13*'Unit Economics'!$B$9-Premissas!$B$21 -> 9249.7871 | H13: =H12*(1-Premissas!$B$6)+Premissas!$B$31 -> 279.73043 | I13: =H13*Premissas!$B$5 -> 27133.852 | J13: =H13*'Unit Economics'!$B$9-Premissas!$B$21 -> 22716.17
A14: 10 | B14: =B13*(1-Premissas!$B$6)+Premissas!$B$29 -> 43.762646 | C14: =B14*Premissas!$B$5 -> 4244.9766 | D14: =B14*'Unit Economics'!$B$9-Premissas!$B$21 -> 2836.8278 | E14: =E13*(1-Premissas!$B$6)+Premissas!$B$30 -> 131.28794 | F14: =E14*Premissas!$B$5 -> 12734.93 | G14: =E14*'Unit Economics'!$B$9-Premissas!$B$21 -> 10210.484 | H14: =H13*(1-Premissas!$B$6)+Premissas!$B$31 -> 306.33852 | I14: =H14*Premissas!$B$5 -> 29714.836 | J14: =H14*'Unit Economics'!$B$9-Premissas!$B$21 -> 24957.795
A15: 11 | B15: =B14*(1-Premissas!$B$6)+Premissas!$B$29 -> 47.449766 | C15: =B15*Premissas!$B$5 -> 4602.6273 | D15: =B15*'Unit Economics'!$B$9-Premissas!$B$21 -> 3147.453 | E15: =E14*(1-Premissas!$B$6)+Premissas!$B$30 -> 142.3493 | F15: =E15*Premissas!$B$5 -> 13807.882 | G15: =E15*'Unit Economics'!$B$9-Premissas!$B$21 -> 11142.359 | H15: =H14*(1-Premissas!$B$6)+Premissas!$B$31 -> 332.14836 | I15: =H15*Premissas!$B$5 -> 32218.391 | J15: =H15*'Unit Economics'!$B$9-Premissas!$B$21 -> 27132.171
A16: 12 | B16: =B15*(1-Premissas!$B$6)+Premissas!$B$29 -> 51.026273 | C16: =B16*Premissas!$B$5 -> 4949.5485 | D16: =B16*'Unit Economics'!$B$9-Premissas!$B$21 -> 3448.7594 | E16: =E15*(1-Premissas!$B$6)+Premissas!$B$30 -> 153.07882 | F16: =E16*Premissas!$B$5 -> 14848.645 | G16: =E16*'Unit Economics'!$B$9-Premissas!$B$21 -> 12046.278 | H16: =H15*(1-Premissas!$B$6)+Premissas!$B$31 -> 357.18391 | I16: =H16*Premissas!$B$5 -> 34646.839 | J16: =H16*'Unit Economics'!$B$9-Premissas!$B$21 -> 29241.316
A18: Clientes = base do mês anterior menos churn, mais novos clientes do cenário.
A19: Resultado = margem de contribuição total menos custo fixo. Não inclui pró-labore.
A20: As taxas de aquisição são premissa, não previsão. Ajuste na aba Premissas assim que houver dado real.
A23: LEGENDA
A24: Amarelo com texto azul = entrada editável • Preto = fórmula • Verde = valor de outra aba

Sheet Construção 90 dias
A1: Desembolso do período de construção
A2: Custo em caixa dos 90 dias até o lançamento. Não inclui remuneração dos sócios.
A4: Item | B4: Mínimo | C4: Máximo | D4: Observação
A5: Abertura de CNPJ e contabilidade (3 meses) | B5: 2400 | C5: 2400 | D5: Abertura ~R$1.500 + R$300/mês.
A6: Assessoria jurídica | B6: 3000 | C6: 6000 | D6: Acordo de quotistas e parecer sobre canais. Faixa ampla.
A7: Infraestrutura durante o desenvolvimento | B7: 180 | C7: 180 | D7: VPS pequena por 3 meses.
A8: Domínio, e-mail e ferramentas | B8: 450 | C8: 450 | D8: Maior parte em free tier.
A9: Reserva para imprevistos | B9: 1000 | C9: 1000 | D9: Estimativa própria.
A10: Total | B10: =SUM(B5:B9) -> 7030 | C10: =SUM(C5:C9) -> 10030
A12: COMPARAÇÃO
A13: Meses de custo fixo cobertos pelo desembolso máximo | B13: =C10/Premissas!B21 -> 11.8 | D13: Quanto tempo o valor da construção sustentaria a operação já no ar.
A16: LEGENDA
A17: Amarelo com texto azul = entrada editável • Preto = fórmula • Verde = valor de outra aba
